[
    {
      "id": "STU1001",
      "name": "Shaked Grunfeld"
    },
    {
      "id": "STU1002",
      "name": "Niv Greenberg"
    },
    {
      "id": "STU1003",
      "name": "Elon Musk"
    },
    {
      "id": "STU1004",
      "name": "Shalom Hahelech"
    },
    {
      "id": "STU1005",
      "name": "Yossi Bar"
    },
    {
      "id": "STU1006",
      "name": "Moshe Shick"
    },
    {
      "id": "STU1007",
      "name": "Yair Arbel"
    },
    {
      "id": "STU1008",
      "name": "Yair Arbel"
    },
    {
      "id": "STU1009",
      "name": "Yair Arbel"
    }
  ]